odoo8_addon_product_variant_sale_delay-8.0.1.0.0-py2.7-nspkg.pth
odoo8_addon_product_variant_sale_delay-8.0.1.0.0.dist-info/DESCRIPTION.rst
odoo8_addon_product_variant_sale_delay-8.0.1.0.0.dist-info/METADATA
odoo8_addon_product_variant_sale_delay-8.0.1.0.0.dist-info/RECORD
odoo8_addon_product_variant_sale_delay-8.0.1.0.0.dist-info/WHEEL
odoo8_addon_product_variant_sale_delay-8.0.1.0.0.dist-info/metadata.json
odoo8_addon_product_variant_sale_delay-8.0.1.0.0.dist-info/namespace_packages.txt
odoo8_addon_product_variant_sale_delay-8.0.1.0.0.dist-info/top_level.txt
odoo_addons/product_variant_sale_delay/README.rst
odoo_addons/product_variant_sale_delay/__init__.py
odoo_addons/product_variant_sale_delay/__openerp__.py
odoo_addons/product_variant_sale_delay/hooks.py
odoo_addons/product_variant_sale_delay/i18n/it.po
odoo_addons/product_variant_sale_delay/models/__init__.py
odoo_addons/product_variant_sale_delay/models/product_product.py
odoo_addons/product_variant_sale_delay/models/product_template.py
odoo_addons/product_variant_sale_delay/static/description/icon.png
odoo_addons/product_variant_sale_delay/tests/__init__.py
odoo_addons/product_variant_sale_delay/tests/test_product_variant_sale_delay.py
